pcwldocker/__init__.py
pcwldocker/origin.tar.xz
pcwldocker-0.1.0.dist-info/LICENSE
pcwldocker-0.1.0.dist-info/METADATA
pcwldocker-0.1.0.dist-info/WHEEL
pcwldocker-0.1.0.dist-info/top_level.txt
pcwldocker-0.1.0.dist-info/RECORD
